wyn_agent_s/__init__.py
wyn_agent_s/helper.py
wyn_agent_s/list_of_apis.py
wyn_agent_s/main.py
wyn_agent_s/metadata.json
wyn_agent_s-0.1.2.dist-info/LICENSE
wyn_agent_s-0.1.2.dist-info/METADATA
wyn_agent_s-0.1.2.dist-info/WHEEL
wyn_agent_s-0.1.2.dist-info/RECORD
