Metadata-Version: 2.1
Name: wyn-agent-s
Version: 0.1.2
Summary: 
Author: eagle0504
Author-email: eagle0504@gmail.com
Requires-Python: >=3.9,<4.0
Classifier: Programming Language :: Python :: 3
Classifier: Programming Language :: Python :: 3.9
Classifier: Programming Language :: Python :: 3.10
Classifier: Programming Language :: Python :: 3.11
Classifier: Programming Language :: Python :: 3.12
Requires-Dist: PyAutoGUI (==0.9.54)
Requires-Dist: anthropic (==0.45.0)
Requires-Dist: fpdf (==1.7.2)
Requires-Dist: google-search-results (>=2.4.2,<3.0.0)
Requires-Dist: matplotlib (>=3.9.0,<4.0.0)
Requires-Dist: openai (>=1.44.1,<2.0.0)
Requires-Dist: python-docx (==1.1.2)
Requires-Dist: serpapi (>=0.1.5,<0.2.0)
Requires-Dist: twilio (>=9.3.0,<10.0.0)
Requires-Dist: web-browser (==0.0.1)
Requires-Dist: yfinance (==0.2.50)
